AUTHORS.rst
CHANGES.rst
LICENSE
README.rst
setup.cfg
setup.py
dnb_urn_service/__init__.py
dnb_urn_service/errors.py
dnb_urn_service/request.py
dnb_urn_service/rest_client.py
dnb_urn_service.egg-info/PKG-INFO
dnb_urn_service.egg-info/SOURCES.txt
dnb_urn_service.egg-info/dependency_links.txt
dnb_urn_service.egg-info/not-zip-safe
dnb_urn_service.egg-info/requires.txt
dnb_urn_service.egg-info/top_level.txt
tests/test_dnb_urn_service.py