Metadata-Version: 2.1
Name: dnb-urn-service
Version: 0.1.6
Summary: "Python API client wrapper for the DNB URN service API"
Home-page: https://github.com/ulbmuenster/dnb-urn-service
Author: University of Münster
Author-email: forschungsdaten@uni-muenster.de
License: MIT
Keywords: invenio rdm data model
Platform: any
Classifier: Development Status :: 3 - Alpha
Requires-Python: >=3.9
License-File: LICENSE
License-File: AUTHORS.rst
Requires-Dist: jsonschema>=3.0.0
Requires-Dist: lxml>=4.5.0
Requires-Dist: requests>=2.12.2
Requires-Dist: idutils>=1.2.0
Provides-Extra: tests
Requires-Dist: responses>=0.10.6; extra == "tests"
Requires-Dist: mock>=1.3.0; extra == "tests"
Requires-Dist: pytest>=7.1.3; extra == "tests"
Requires-Dist: pytest-black>=0.3.12; extra == "tests"
Requires-Dist: pytest-invenio>=1.4.0; extra == "tests"
